xcresult/__init__.py
xcresult/command_line.py
xcresult/exceptions.py
xcresult/junit_writer.py
xcresult/model.py
xcresult/py.typed
xcresult/xcresult_base.py
xcresult/xcresults.py
xcresult/xcresulttool.py
xcresult-26.0.1.dist-info/LICENSE
xcresult-26.0.1.dist-info/METADATA
xcresult-26.0.1.dist-info/WHEEL
xcresult-26.0.1.dist-info/entry_points.txt
xcresult-26.0.1.dist-info/RECORD
