Metadata-Version: 2.1
Name: xcresult
Version: 26.0.1
Summary: An xcresult parser.
Home-page: https://github.com/dalemyers/xcresult
License: MIT
Keywords: xcresult,parser,xcode
Author: Dale Myers
Author-email: dale@myers.io
Requires-Python: >=3.10,<4.0
Classifier: Development Status :: 5 - Production/Stable
Classifier: Intended Audience :: Developers
Classifier: License :: OSI Approved :: MIT License
Classifier: Programming Language :: Python :: 3
Classifier: Programming Language :: Python :: 3.10
Classifier: Programming Language :: Python :: 3.11
Classifier: Programming Language :: Python :: 3.12
Classifier: Programming Language :: Python :: 3.13
Classifier: Topic :: Software Development :: Libraries
Requires-Dist: lxml (>=5.0.0,<6.0.0)
Project-URL: Repository, https://github.com/dalemyers/xcresult
